{
  "name": "site_services",
  "template": "albums",
  "title": "Our Tools",
  "keywords": "VolBrain Tutorials",
  "subtitle": "A short description of each service",
  "metas": {
    "icon": "fa fa-life-ring fa-4x",
    "more_label": "More",
    "image_url": "/static/img/banner.png"
  },
  "contents": [
    "Tuto Content"
  ],
  "children": [
    {
      "name": "volbrain",
      "title": "VolBrain",
      "subtitle": "VolBrain Tutorial",
      "contents": [
        "volBrain is a pipeline of processes aimed to automatically analyze MRI brain data."
      ],
      "metas": {
        "image_url": "/static/assets/img/pipelines/volbrain/volbrain_blue.jpg",
        "image_alt": "volbrain_blue",
        "action_url": "/pages/tutorials/volbrain",
        "action_key": "Read More ..."
      }
    },
    {
      "name": "ceres",
      "title": "CERES",
      "subtitle": "CERES Tutorial",
      "contents": [
        "Ceres is a pipeline to automatically analyze Cerebellum MRI brain data."
      ],
      "metas": {
        "image_url": "/static/assets/img/pipelines/ceres/ceres_blue.jpg",
        "image_alt": "ceres_blue",
        "action_url": "/pages/tutorials/ceres",
        "action_key": "Read More ..."
      }
    },
    {
      "name": "hips",
      "title": "HIPS",
      "subtitle": "HIPS Tutorial",
      "contents": [
        "HIPS is a pipeline for automatic hippocampus subfield segmetnation from monomodal (T1) of multimodal MRI data (T1 + T2)."
      ],
      "metas": {
        "image_url": "/static/assets/img/pipelines/hips/hips_blue.jpg",
        "image_alt": "hips_blue",
        "action_url": "/pages/tutorials/hips",
        "action_key": "Read More ..."
      }
    },
    {
      "name": "lesionbrain",
      "title": "LesionBrain",
      "subtitle": "LesionBrain Tutorial",
      "contents": [
        "LesionBrain is a pipeline to automatically segment white matter lesions from MRI data(T1 + FLAIR)."
      ],
      "metas": {
        "image_url": "/static/assets/img/pipelines/lesionbrain/lesionbrain_blue.jpg",
        "image_alt": "lesionbrain_blue",
        "action_url": "/pages/tutorials/lesionbrain",
        "action_key": "Read More ..."
      }
    }
  ]
}